moesiftornado/__init__.py
moesiftornado/app_config.py
moesiftornado/client_ip.py
moesiftornado/event_mapper.py
moesiftornado/logger_helper.py
moesiftornado/middleware.py
moesiftornado/parse_body.py
moesiftornado/send_batch_events.py
moesiftornado/update_companies.py
moesiftornado/update_users.py
moesiftornado-0.1.4.dist-info/LICENSE
moesiftornado-0.1.4.dist-info/METADATA
moesiftornado-0.1.4.dist-info/WHEEL
moesiftornado-0.1.4.dist-info/top_level.txt
moesiftornado-0.1.4.dist-info/RECORD
