Metadata-Version: 2.1
Name: moesiftornado
Version: 0.1.4
Summary: Moesif Middleware for Python Tornado based platforms
Home-page: https://www.moesif.com/docs/server-integration/python-tornado/
Author: Moesif, Inc
Author-email: keyur@moesif.com
License: Apache Software License
Keywords: log analysis restful api development debug tornado http middleware
Platform: UNKNOWN
Classifier: Development Status :: 4 - Beta
Classifier: Intended Audience :: Developers
Classifier: Topic :: Internet :: Log Analysis
Classifier: Topic :: Software Development :: Debuggers
Classifier: Topic :: Software Development :: Libraries
Classifier: Topic :: Internet :: WWW/HTTP
Classifier: License :: OSI Approved :: Apache Software License
Classifier: Programming Language :: Python :: 2
Classifier: Programming Language :: Python :: 2.6
Classifier: Programming Language :: Python :: 2.7
Classifier: Programming Language :: Python :: 3
Classifier: Programming Language :: Python :: 3.3
Classifier: Programming Language :: Python :: 3.4
Classifier: Programming Language :: Python :: 3.5
Requires-Dist: requests
Requires-Dist: isodatetimehandler
Requires-Dist: moesifapi
Requires-Dist: apscheduler
Provides-Extra: dev
Provides-Extra: test
Requires-Dist: nose ; extra == 'test'
